vane/__init__.py
vane/vane.py
vane/message_formatter/__init__.py
vane/message_formatter/message_formatter.py
vane_native-0.1.0a4.dist-info/licenses/LICENSE
vane_native-0.1.0a4.dist-info/METADATA
vane_native-0.1.0a4.dist-info/WHEEL
vane_native-0.1.0a4.dist-info/top_level.txt
vane_native-0.1.0a4.dist-info/RECORD
